gworkspace/__init__.py
gworkspace/py.typed
gworkspace/server.py
puremcp_google_workspace-0.1.0.dist-info/METADATA
puremcp_google_workspace-0.1.0.dist-info/WHEEL
puremcp_google_workspace-0.1.0.dist-info/entry_points.txt
puremcp_google_workspace-0.1.0.dist-info/licenses/LICENSE
puremcp_google_workspace-0.1.0.dist-info/RECORD
