Metadata-Version: 2.4
Name: puremcp-google-workspace
Version: 0.1.0
Summary: MCP server for Google Workspace (Gmail, Drive, Calendar, Docs, Sheets, and more)
Project-URL: Homepage, https://github.com/puremcp/google-workspace
Project-URL: Repository, https://github.com/puremcp/google-workspace
Project-URL: Issues, https://github.com/puremcp/google-workspace/issues
Author: puremcp
License: Apache-2.0
License-File: LICENSE
Keywords: ai,calendar,docs,drive,gmail,google,llm,mcp,sheets,workspace
Classifier: Development Status :: 3 - Alpha
Classifier: Intended Audience :: Developers
Classifier: License :: OSI Approved :: Apache Software License
Classifier: Programming Language :: Python :: 3
Classifier: Programming Language :: Python :: 3.10
Classifier: Programming Language :: Python :: 3.11
Classifier: Programming Language :: Python :: 3.12
Classifier: Programming Language :: Python :: 3.13
Requires-Python: >=3.10
Requires-Dist: fastmcp>=2.14.1
Requires-Dist: google-api-python-client>=2.0.0
Requires-Dist: google-auth-httplib2>=0.2.0
Requires-Dist: google-auth-oauthlib>=1.0.0
Requires-Dist: google-auth>=2.0.0
